pinjected_notion/__init__.py
pinjected_notion/notion_db_util.py
pinjected_notion/notion_db_util_v2.py
pinjected_notion-0.1.4.dist-info/METADATA
pinjected_notion-0.1.4.dist-info/WHEEL
pinjected_notion-0.1.4.dist-info/RECORD
