Metadata-Version: 2.1
Name: pinjected-notion
Version: 0.1.4
Summary: 
Author: proboscis
Author-email: nameissoap@gmail.com
Requires-Python: >=3.11,<4.0
Classifier: Programming Language :: Python :: 3
Classifier: Programming Language :: Python :: 3.11
Requires-Dist: boto3 (>=1.34.27,<2.0.0)
Requires-Dist: jupyter (>=1.0.0,<2.0.0)
Requires-Dist: notion-client (>=2.2.1,<3.0.0)
Requires-Dist: notion-database (>=1.1.0,<2.0.0)
Requires-Dist: numpy (>=1.26.3,<2.0.0)
Requires-Dist: pandas (>=2.2.0,<3.0.0)
Requires-Dist: pillow (>=10.2.0,<11.0.0)
Requires-Dist: pinjected (>=0.1.166,<0.2.0)
Requires-Dist: proboscis-image-util (>=0.1.0,<0.2.0)
Requires-Dist: tqdm (>=4.66.1,<5.0.0)
